README.md
setup.py
django_pmedien_all/__init__.py
django_pmedien_all.egg-info/PKG-INFO
django_pmedien_all.egg-info/SOURCES.txt
django_pmedien_all.egg-info/dependency_links.txt
django_pmedien_all.egg-info/requires.txt
django_pmedien_all.egg-info/top_level.txt