Metadata-Version: 1.0
Name: django-pmedien-all
Version: 0.1
Summary: All Pmedien Packages
Home-page: http://www.pmedien.com
Author: pmedien GmbH
Author-email: nomail@pmedien.com
License: MIT
Platform: UNKNOWN
